odoo8_addon_account_group_invoice_lines-8.0.1.1.0.99.dev21-py2.7-nspkg.pth
odoo8_addon_account_group_invoice_lines-8.0.1.1.0.99.dev21.dist-info/METADATA
odoo8_addon_account_group_invoice_lines-8.0.1.1.0.99.dev21.dist-info/RECORD
odoo8_addon_account_group_invoice_lines-8.0.1.1.0.99.dev21.dist-info/WHEEL
odoo8_addon_account_group_invoice_lines-8.0.1.1.0.99.dev21.dist-info/namespace_packages.txt
odoo8_addon_account_group_invoice_lines-8.0.1.1.0.99.dev21.dist-info/top_level.txt
odoo_addons/account_group_invoice_lines/README.rst
odoo_addons/account_group_invoice_lines/__init__.py
odoo_addons/account_group_invoice_lines/__openerp__.py
odoo_addons/account_group_invoice_lines/account.py
odoo_addons/account_group_invoice_lines/account_view.xml
odoo_addons/account_group_invoice_lines/i18n/account_group_invoice_lines.pot
odoo_addons/account_group_invoice_lines/i18n/ar.po
odoo_addons/account_group_invoice_lines/i18n/bg.po
odoo_addons/account_group_invoice_lines/i18n/bs.po
odoo_addons/account_group_invoice_lines/i18n/ca.po
odoo_addons/account_group_invoice_lines/i18n/ca_ES.po
odoo_addons/account_group_invoice_lines/i18n/cs.po
odoo_addons/account_group_invoice_lines/i18n/da.po
odoo_addons/account_group_invoice_lines/i18n/de.po
odoo_addons/account_group_invoice_lines/i18n/el_GR.po
odoo_addons/account_group_invoice_lines/i18n/en_GB.po
odoo_addons/account_group_invoice_lines/i18n/es.po
odoo_addons/account_group_invoice_lines/i18n/es_CR.po
odoo_addons/account_group_invoice_lines/i18n/es_EC.po
odoo_addons/account_group_invoice_lines/i18n/es_MX.po
odoo_addons/account_group_invoice_lines/i18n/es_PE.po
odoo_addons/account_group_invoice_lines/i18n/es_VE.po
odoo_addons/account_group_invoice_lines/i18n/et.po
odoo_addons/account_group_invoice_lines/i18n/fi.po
odoo_addons/account_group_invoice_lines/i18n/fr.po
odoo_addons/account_group_invoice_lines/i18n/fr_CA.po
odoo_addons/account_group_invoice_lines/i18n/fr_CH.po
odoo_addons/account_group_invoice_lines/i18n/gl.po
odoo_addons/account_group_invoice_lines/i18n/hr.po
odoo_addons/account_group_invoice_lines/i18n/hr_HR.po
odoo_addons/account_group_invoice_lines/i18n/hu.po
odoo_addons/account_group_invoice_lines/i18n/id.po
odoo_addons/account_group_invoice_lines/i18n/it.po
odoo_addons/account_group_invoice_lines/i18n/ja.po
odoo_addons/account_group_invoice_lines/i18n/lt.po
