Metadata-Version: 2.1
Name: odoo8-addon-account-group-invoice-lines
Version: 8.0.1.1.0.99.dev21
Summary: Add option to group invoice line per account
Home-page: http://www.syleam.fr/
Author: SYLEAM,Akretion,Odoo Community Association (OCA)
Author-email: support@odoo-community.org
License: AGPL-3
Platform: UNKNOWN
Classifier: Programming Language :: Python
Classifier: Framework :: Odoo
Classifier: License :: OSI Approved :: GNU Affero General Public License v3
Requires-Python: ~=2.7
Requires-Dist: odoo (<9.0a,>=8.0a)
